LICENSE
MANIFEST.in
README.md
pyproject.toml
setup.py
src/ccpm.c
src/ccpm.h
src/crazy_cpm/__init__.py
src/crazy_cpm/_ccpm.c
src/crazy_cpm/_ccpm.pyx
src/crazy_cpm/net_model.py
src/crazy_cpm.egg-info/PKG-INFO
src/crazy_cpm.egg-info/SOURCES.txt
src/crazy_cpm.egg-info/dependency_links.txt
src/crazy_cpm.egg-info/not-zip-safe
src/crazy_cpm.egg-info/requires.txt
src/crazy_cpm.egg-info/top_level.txt
tests/test_net_model.py