Metadata-Version: 2.4
Name: crazy_cpm
Version: 0.99.0
Summary: Crazy Critical Path Method
Author-email: anonimous <shkolnick-kun@gmail.com>
License:                     GNU GENERAL PUBLIC LICENSE
Project-URL: Homepage, https://github.com/shkolnick-kun/crazy_cpm
Project-URL: Documentation, https://github.com/shkolnick-kun/crazy_cpm
Project-URL: Repository, https://github.com/shkolnick-kun/crazy_cpm
Project-URL: Issues, https://github.com/shkolnick-kun/crazy_cpm/issues
Keywords: cpm,scheduling,critical-path
Classifier: Development Status :: 3 - Alpha
Classifier: License :: OSI Approved :: GNU General Public License v3 (GPLv3)
Classifier: Intended Audience :: Science/Research
Classifier: Topic :: Scientific/Engineering
Classifier: Topic :: Scientific/Engineering :: Mathematics
Classifier: Natural Language :: English
Classifier: Operating System :: OS Independent
Classifier: Programming Language :: C
Classifier: Programming Language :: Cython
Classifier: Programming Language :: Python
Classifier: Programming Language :: Python :: 3
Classifier: Programming Language :: Python :: 3.9
Classifier: Programming Language :: Python :: 3.10
Classifier: Programming Language :: Python :: 3.11
Classifier: Programming Language :: Python :: 3.12
Classifier: Programming Language :: Python :: 3 :: Only
Classifier: Programming Language :: Python :: Implementation :: CPython
Requires-Python: <4,>=3.9
License-File: LICENSE
Requires-Dist: betapert>=0.1.5
Requires-Dist: graphviz>=0.14.2
Requires-Dist: numpy<2.0,>=1.17
Requires-Dist: pandas>=1.0
Provides-Extra: dev
Requires-Dist: pytest; extra == "dev"
Provides-Extra: docs
Requires-Dist: sphinx; extra == "docs"
Requires-Dist: sphinx-rtd-theme; extra == "docs"
Dynamic: license-file
